saldet/__init__.py
saldet/dataset/__init__.py
saldet/dataset/inference.py
saldet/dataset/saliency.py
saldet/experiment/__init__.py
saldet/experiment/inference.py
saldet/experiment/train.py
saldet/io/__init__.py
saldet/io/config.py
saldet/io/image.py
saldet/loss/__init__.py
saldet/loss/_factory.py
saldet/loss/attn_guided.py
saldet/loss/bce_iou_loss.py
saldet/loss/edge_saliency_loss.py
saldet/loss/multi_bce.py
saldet/loss/pg.py
saldet/lr_scheduler/__init__.py
saldet/lr_scheduler/lr_scheduler.py
saldet/models/__init__.py
saldet/models/_factory.py
saldet/models/models/__init__.py
saldet/models/models/pfan.py
saldet/models/models/pgnet.py
saldet/models/models/resnet.py
saldet/models/models/swin.py
saldet/models/models/u2net.py
saldet/ops/__init__.py
saldet/ops/tensor.py
saldet/optimizer/__init__.py
saldet/optimizer/optimizer.py
saldet/pl/__init__.py
saldet/pl/data.py
saldet/pl/model.py
saldet/plot/__init__.py
saldet/plot/plot.py
saldet/trainer/__init__.py
saldet/trainer/callbacks.py
saldet/transform/__init__.py
saldet/transform/transform.py
saldet/utils/__init__.py
saldet/utils/device.py
saldet/utils/time.py
saldet-0.6.1.dist-info/LICENSE
saldet-0.6.1.dist-info/METADATA
saldet-0.6.1.dist-info/WHEEL
saldet-0.6.1.dist-info/RECORD
